MANIFEST.in
README.txt
setup.cfg
setup.py
collective/__init__.py
collective.z3cform.quantitywidget.egg-info/PKG-INFO
collective.z3cform.quantitywidget.egg-info/SOURCES.txt
collective.z3cform.quantitywidget.egg-info/dependency_links.txt
collective.z3cform.quantitywidget.egg-info/entry_points.txt
collective.z3cform.quantitywidget.egg-info/namespace_packages.txt
collective.z3cform.quantitywidget.egg-info/not-zip-safe
collective.z3cform.quantitywidget.egg-info/paster_plugins.txt
collective.z3cform.quantitywidget.egg-info/requires.txt
collective.z3cform.quantitywidget.egg-info/top_level.txt
collective/z3cform/__init__.py
collective/z3cform/quantitywidget/__init__.py
collective/z3cform/quantitywidget/configure.zcml
collective/z3cform/quantitywidget/interfaces.py
collective/z3cform/quantitywidget/browser/__init__.py
collective/z3cform/quantitywidget/browser/configure.zcml
collective/z3cform/quantitywidget/browser/widget.py
collective/z3cform/quantitywidget/browser/templates/quantity_input.pt
collective/z3cform/quantitywidget/locales/collective.z3cform.quantitywidget.pot
collective/z3cform/quantitywidget/locales/update.sh
collective/z3cform/quantitywidget/locales/en/LC_MESSAGES/collective.z3cform.quantitywidget.mo
collective/z3cform/quantitywidget/locales/fr/LC_MESSAGES/collective.z3cform.quantitywidget.mo
collective/z3cform/quantitywidget/locales/fr/LC_MESSAGES/collective.z3cform.quantitywidget.po