Metadata-Version: 1.1
Name: collective.z3cform.quantitywidget
Version: 1.0
Summary: HTML5 number type input implementation with unit
Home-page: http://svn.plone.org/svn/collective/
Author: Martronic SA
Author-email: martronic@martronic.ch
License: GPL
Keywords: number,input,widget,quantity
Platform: UNKNOWN
Classifier: Framework :: Plone
Classifier: Programming Language :: Python
